{
  "version": "1",
  "cognitoConfig": {
    "identityPoolName": "wildrydese8e02710_identitypool_e8e02710",
    "allowUnauthenticatedIdentities": false,
    "resourceNameTruncated": "wildrye8e02710",
    "userPoolName": "wildrydese8e02710_userpool_e8e02710",
    "autoVerifiedAttributes": [
      "email"
    ],
    "mfaConfiguration": "OFF",
    "mfaTypes": [
      "SMS Text Message"
    ],
    "smsAuthenticationMessage": "Your authentication code is {####}",
    "smsVerificationMessage": "Your verification code is {####}",
    "emailVerificationSubject": "Your verification code",
    "emailVerificationMessage": "Your verification code is {####}",
    "defaultPasswordPolicy": false,
    "passwordPolicyMinLength": 8,
    "passwordPolicyCharacters": [],
    "requiredAttributes": [
      "email"
    ],
    "aliasAttributes": [],
    "userpoolClientGenerateSecret": false,
    "userpoolClientRefreshTokenValidity": 30,
    "userpoolClientWriteAttributes": [
      "email"
    ],
    "userpoolClientReadAttributes": [
      "email"
    ],
    "userpoolClientLambdaRole": "wildrye8e02710_userpoolclient_lambda_role",
    "userpoolClientSetAttributes": false,
    "sharedId": "e8e02710",
    "resourceName": "wildrydese8e02710",
    "authSelections": "identityPoolAndUserPool",
    "useDefault": "default",
    "userPoolGroupList": [],
    "serviceName": "Cognito",
    "useEnabledMfas": false
  }
}